src/__init__.py
src/pingnet.py
pingnet-0.4.5.dist-info/LICENSE.txt
pingnet-0.4.5.dist-info/METADATA
pingnet-0.4.5.dist-info/WHEEL
pingnet-0.4.5.dist-info/entry_points.txt
pingnet-0.4.5.dist-info/top_level.txt
pingnet-0.4.5.dist-info/RECORD
