Metadata-Version: 2.1
Name: pingnet
Version: 0.4.5
Summary: Script to ping network address(CIDR), IP address, hostname
Home-page: https://github.com/skndmx/pingnet
Author: Kevin Jin
Author-email: skndmx@gmail.com
Project-URL: Bug Tracker, https://github.com/skndmx/pingnet/issues
Project-URL: repository, https://github.com/skndmx/pingnet
Classifier: Programming Language :: Python :: 3
Classifier: License :: OSI Approved :: MIT License
Classifier: Operating System :: OS Independent
License-File: LICENSE.txt
